genai_processors_pydantic/__init__.py
genai_processors_pydantic/validator.py
genai_processors_pydantic/tests/__init__.py
genai_processors_pydantic/tests/test_validator.py
genai_processors_pydantic-0.1.2.dist-info/METADATA
genai_processors_pydantic-0.1.2.dist-info/WHEEL
genai_processors_pydantic-0.1.2.dist-info/licenses/LICENSE
genai_processors_pydantic-0.1.2.dist-info/RECORD
