Metadata-Version: 2.4
Name: genai-processors-pydantic
Version: 0.1.2
Summary: A Pydantic validator processor for Google's genai-processors framework
Project-URL: Homepage, https://github.com/mbeacom/genai-processors-pydantic
Project-URL: Repository, https://github.com/mbeacom/genai-processors-pydantic.git
Project-URL: Issues, https://github.com/mbeacom/genai-processors-pydantic/issues
Project-URL: Documentation, https://github.com/mbeacom/genai-processors-pydantic#readme
Author-email: Mark Beacom <m@beacom.dev>
License: Apache-2.0
License-File: LICENSE
Keywords: ai,contrib,deepmind,gemini,genai,genai-processors,genai-processors-contrib,generative-ai,google,processor,processors,pydantic,schema,validation
Classifier: Development Status :: 4 - Beta
Classifier: Framework :: Pydantic
Classifier: Intended Audience :: Developers
Classifier: License :: OSI Approved :: Apache Software License
Classifier: Operating System :: OS Independent
Classifier: Programming Language :: Python
Classifier: Programming Language :: Python :: 3
Classifier: Programming Language :: Python :: 3.11
Classifier: Programming Language :: Python :: 3.12
Classifier: Programming Language :: Python :: 3.13
Classifier: Topic :: Scientific/Engineering :: Artificial Intelligence
Classifier: Topic :: Software Development :: Libraries :: Python Modules
Requires-Python: >=3.11
Requires-Dist: genai-processors>=1.0.4
Requires-Dist: pydantic>=2.0
